semantic_search/__init__.py
semantic_search/database_factory.py
semantic_search/search.py
pysemantic_search-0.1.0.dist-info/LICENSE
pysemantic_search-0.1.0.dist-info/METADATA
pysemantic_search-0.1.0.dist-info/WHEEL
pysemantic_search-0.1.0.dist-info/top_level.txt
pysemantic_search-0.1.0.dist-info/RECORD
