Metadata-Version: 2.2
Name: pysemantic-search
Version: 0.1.0
Summary: A semantic search library using FAISS and multiple database backends.
Home-page: https://github.com/kunci115/semantic-search
Author: Rino Alfian
Author-email: rino.alpin@gmail.com
Classifier: Programming Language :: Python :: 3
Classifier: License :: OSI Approved :: MIT License
Classifier: Operating System :: OS Independent
Requires-Python: >=3.7
License-File: LICENSE
Requires-Dist: certifi==2025.1.31
Requires-Dist: charset-normalizer==3.4.1
Requires-Dist: dnspython==2.7.0
Requires-Dist: faiss-cpu==1.10.0
Requires-Dist: filelock==3.17.0
Requires-Dist: fsspec==2025.2.0
Requires-Dist: huggingface-hub==0.29.1
Requires-Dist: idna==3.10
Requires-Dist: Jinja2==3.1.5
Requires-Dist: joblib==1.4.2
Requires-Dist: MarkupSafe==3.0.2
Requires-Dist: mpmath==1.3.0
Requires-Dist: mysql-connector-python==9.2.0
Requires-Dist: networkx==3.4.2
Requires-Dist: numpy==2.2.3
Requires-Dist: packaging==24.2
Requires-Dist: pillow==11.1.0
Requires-Dist: psycopg2-binary==2.9.10
Requires-Dist: pymongo==4.11.1
Requires-Dist: PyYAML==6.0.2
Requires-Dist: redis==5.2.1
Requires-Dist: regex==2024.11.6
Requires-Dist: requests==2.32.3
Requires-Dist: safetensors==0.5.2
Requires-Dist: scikit-learn==1.6.1
Requires-Dist: scipy==1.15.2
Requires-Dist: sentence-transformers==3.4.1
Requires-Dist: setuptools==75.8.0
Requires-Dist: sympy==1.13.1
Requires-Dist: threadpoolctl==3.5.0
Requires-Dist: tokenizers==0.21.0
Requires-Dist: torch==2.6.0
Requires-Dist: tqdm==4.67.1
Requires-Dist: transformers==4.49.0
Requires-Dist: typing_extensions==4.12.2
Requires-Dist: urllib3==2.3.0
Dynamic: author
Dynamic: author-email
Dynamic: classifier
Dynamic: description
Dynamic: description-content-type
Dynamic: home-page
Dynamic: requires-dist
Dynamic: requires-python
Dynamic: summary
